nikel_py/__init__.py
nikel_py/buildings.py
nikel_py/courses.py
nikel_py/evals.py
nikel_py/exams.py
nikel_py/food.py
nikel_py/parking.py
nikel_py/programs.py
nikel_py/services.py
nikel_py/textbooks.py
nikel_py/utils/__init__.py
nikel_py/utils/_constants.py
nikel_py/utils/_getter.py
nikel_py/utils/_urlparser.py
nikel_py/utils/errors.py
nikel_py-0.1.1.dist-info/METADATA
nikel_py-0.1.1.dist-info/WHEEL
nikel_py-0.1.1.dist-info/top_level.txt
nikel_py-0.1.1.dist-info/RECORD
